grimoire_model/__init__.py
grimoire_model/logging.py
grimoire_model/core/__init__.py
grimoire_model/core/exceptions.py
grimoire_model/core/model.py
grimoire_model/core/primitive_registry.py
grimoire_model/core/registry.py
grimoire_model/core/schema.py
grimoire_model/resolvers/__init__.py
grimoire_model/resolvers/derived.py
grimoire_model/resolvers/template.py
grimoire_model/utils/__init__.py
grimoire_model/utils/inheritance.py
grimoire_model/utils/paths.py
grimoire_model/validation/__init__.py
grimoire_model/validation/validators.py
grimoire_model-0.3.3.dist-info/licenses/LICENSE
grimoire_model-0.3.3.dist-info/METADATA
grimoire_model-0.3.3.dist-info/WHEEL
grimoire_model-0.3.3.dist-info/top_level.txt
grimoire_model-0.3.3.dist-info/RECORD
