Metadata-Version: 2.4
Name: grimoire-model
Version: 0.3.3
Summary: Dict-like model system with schema validation, derived fields, and inheritance for GRIMOIRE
Author-email: The Wyrd One <wyrdbound@proton.me>
License: MIT
Project-URL: Homepage, https://github.com/wyrdbound/grimoire-model
Project-URL: Repository, https://github.com/wyrdbound/grimoire-model
Project-URL: Issues, https://github.com/wyrdbound/grimoire-model/issues
Keywords: gaming,rpg,tabletop,model,validation,schema
Classifier: Development Status :: 3 - Alpha
Classifier: Intended Audience :: Developers
Classifier: License :: OSI Approved :: MIT License
Classifier: Programming Language :: Python :: 3
Classifier: Programming Language :: Python :: 3.8
Classifier: Programming Language :: Python :: 3.9
Classifier: Programming Language :: Python :: 3.10
Classifier: Programming Language :: Python :: 3.11
Classifier: Programming Language :: Python :: 3.12
Classifier: Topic :: Games/Entertainment :: Role-Playing
Classifier: Topic :: Software Development :: Libraries :: Python Modules
Requires-Python: >=3.8
License-File: LICENSE
Requires-Dist: pydantic>=2.0.0
Requires-Dist: pyrsistent>=0.19.0
Requires-Dist: jinja2>=3.1.0
Requires-Dist: pyyaml>=6.0
Requires-Dist: grimoire-logging>=0.1.0
Provides-Extra: dev
Requires-Dist: pytest>=7.0.0; extra == "dev"
Requires-Dist: pytest-cov>=4.0.0; extra == "dev"
Requires-Dist: pytest-mock>=3.0.0; extra == "dev"
Requires-Dist: hypothesis>=6.0.0; extra == "dev"
Requires-Dist: mypy>=1.0.0; extra == "dev"
Requires-Dist: ruff>=0.0.290; extra == "dev"
Provides-Extra: docs
Requires-Dist: sphinx>=4.0.0; extra == "docs"
Requires-Dist: sphinx-rtd-theme>=1.0.0; extra == "docs"
Requires-Dist: sphinxcontrib-napoleon>=0.7; extra == "docs"
Provides-Extra: test
Requires-Dist: pytest>=7.0.0; extra == "test"
Requires-Dist: pytest-cov>=4.0.0; extra == "test"
Requires-Dist: pytest-mock>=3.0.0; extra == "test"
Requires-Dist: hypothesis>=6.0.0; extra == "test"
Dynamic: license-file
